.gitignore
MANIFEST.in
README.rst
setup.cfg
setup.py
docs/HISTORY.txt
docs/LICENSE.GPL
docs/LICENSE.txt
docs/MANUAL.txt
raptus/__init__.py
raptus.article.teaser.egg-info/PKG-INFO
raptus.article.teaser.egg-info/SOURCES.txt
raptus.article.teaser.egg-info/dependency_links.txt
raptus.article.teaser.egg-info/entry_points.txt
raptus.article.teaser.egg-info/namespace_packages.txt
raptus.article.teaser.egg-info/not-zip-safe
raptus.article.teaser.egg-info/requires.txt
raptus.article.teaser.egg-info/top_level.txt
raptus/article/__init__.py
raptus/article/teaser/__init__.py
raptus/article/teaser/configure.zcml
raptus/article/teaser/extender.py
raptus/article/teaser/interfaces.py
raptus/article/teaser/teaser.py
raptus/article/teaser/browser/__init__.py
raptus/article/teaser/browser/configure.zcml
raptus/article/teaser/browser/migrations.py
raptus/article/teaser/browser/migrations.zcml
raptus/article/teaser/browser/teaser.pt
raptus/article/teaser/browser/teaser.py
raptus/article/teaser/browser/teaser_full.gif
raptus/article/teaser/browser/teaser_left.gif
raptus/article/teaser/browser/teaser_right.gif
raptus/article/teaser/i18n/raptus.article-de.mo
raptus/article/teaser/i18n/raptus.article-de.po
raptus/article/teaser/i18n/raptus.article-fr.mo
raptus/article/teaser/i18n/raptus.article-fr.po
raptus/article/teaser/i18n/raptus.article.pot
raptus/article/teaser/profiles/default/metadata.xml
raptus/article/teaser/profiles/default/propertiestool.xml
raptus/article/teaser/profiles/default/viewlets.xml
raptus/article/teaser/upgrades/__init__.py
raptus/article/teaser/upgrades/configure.zcml
raptus/article/teaser/upgrades/profiles.zcml
raptus/article/teaser/upgrades/profiles/10_to_11/propertiestool.xml