Metadata-Version: 1.1
Name: raptus.article.teaser
Version: 2.0b12
Summary: Provides support for a teaser image.
Home-page: https://github.com/Raptus/raptus.article.teaser
Author: Raptus AG
Author-email: dev@raptus.com
License: GPL
Platform: UNKNOWN
Classifier: Programming Language :: Python
Classifier: Topic :: Software Development :: Libraries :: Python Modules
